{"version":"3.8.0","examples":[{"id":"./spec/grocer_spec.rb[1:1:1]","description":"adds a count of one to each item when there are no duplicates","full_description":"Grocer #consolidate_cart adds a count of one to each item when there are no duplicates","status":"passed","file_path":"./spec/grocer_spec.rb","line_number":29,"run_time":0.001529847,"pending_message":null},{"id":"./spec/grocer_spec.rb[1:1:2]","description":"increments count when there are multiple items","full_description":"Grocer #consolidate_cart increments count when there are multiple items","status":"passed","file_path":"./spec/grocer_spec.rb","line_number":38,"run_time":0.000215954,"pending_message":null},{"id":"./spec/grocer_spec.rb[1:2:1:1]","description":"adds a new key, value pair to the cart hash called 'ITEM NAME W/COUPON'","full_description":"Grocer #apply_coupons base case - with perfect coupon (number of items identical): adds a new key, value pair to the cart hash called 'ITEM NAME W/COUPON'","status":"passed","file_path":"./spec/grocer_spec.rb","line_number":63,"run_time":53.653473331,"pending_message":null},{"id":"./spec/grocer_spec.rb[1:2:1:2]","description":"adds the coupon price to the property hash of couponed item","full_description":"Grocer #apply_coupons base case - with perfect coupon (number of items identical): adds the coupon price to the property hash of couponed item","status":"","file_path":"./spec/grocer_spec.rb","line_number":67,"run_time":13.064446335,"pending_message":null}],"summary":{"duration":66.721904475,"example_count":4,"failure_count":0,"pending_count":0,"errors_outside_of_examples_count":0},"summary_line":"4 examples, 0 failures"}